petfinder/__init__.py
petfinder/animals.py
petfinder/auth.py
petfinder/client.py
petfinder/enums.py
petfinder/models.py
petfinder/organizations.py
petfinder/pandas.py
petfinder/query.py
petfinder/schemas.py
petfinder/sql.py
petfinder/storage.py
petfinder/types.py
petfinder/caching/__init__.py
petfinder/caching/core.py
petfinder/caching/backends/__init__.py
petfinder/caching/backends/sqlite.py
scripts/__init__.py
scripts/basic.py
scripts/big_dump.py
scripts/dump_to_csv.py
scripts/dump_to_sqlite.py
scripts/gathering.py
scripts/sqlite_adopted_barnyard.py
scripts/sqlite_adopted_cats.py
scripts/sqlite_adopted_small_furry.py
scripts/view_small_furry.py
petfinder_sdk-0.0.2.dist-info/LICENSE
petfinder_sdk-0.0.2.dist-info/METADATA
petfinder_sdk-0.0.2.dist-info/WHEEL
petfinder_sdk-0.0.2.dist-info/top_level.txt
petfinder_sdk-0.0.2.dist-info/RECORD
