Metadata-Version: 2.1
Name: petfinder-sdk
Version: 0.0.2
Summary: High-performance petfinder API client: async support, efficient caching, query validation, and more
Home-page: https://github.com/phillipdupuis/petfinder-sdk
Author: Phillip Dupuis
Author-email: phillip_dupuis@alumni.brown.edu
License: MIT
Keywords: async
Platform: UNKNOWN
Classifier: Development Status :: 4 - Beta
Classifier: License :: OSI Approved :: MIT License
Classifier: Programming Language :: Python
Classifier: Programming Language :: Python :: 3
Classifier: Programming Language :: Python :: 3 :: Only
Classifier: Programming Language :: Python :: 3.6
Classifier: Programming Language :: Python :: 3.7
Classifier: Programming Language :: Python :: 3.8
Requires-Dist: appdirs
Requires-Dist: httpx
Requires-Dist: pandas
Requires-Dist: pydantic
Requires-Dist: typing-extensions
